pytest_shortcuts.py
pytest_shortcuts-0.4.0.dist-info/LICENSE
pytest_shortcuts-0.4.0.dist-info/METADATA
pytest_shortcuts-0.4.0.dist-info/WHEEL
pytest_shortcuts-0.4.0.dist-info/entry_points.txt
pytest_shortcuts-0.4.0.dist-info/top_level.txt
pytest_shortcuts-0.4.0.dist-info/RECORD
