Metadata-Version: 2.1
Name: pytest-shortcuts
Version: 0.4.0
Summary: Expand command-line shortcuts listed in pytest configuration
Home-page: https://github.com/willhardy/pytest-shortcuts
Author: Will Hardy
Author-email: public@willhardy.com.au
Maintainer: Will Hardy
Maintainer-email: public@willhardy.com.au
License: BSD-3-Clause
Project-URL: Code, https://github.com/willhardy/pytest-shortcuts
Platform: UNKNOWN
Classifier: Development Status :: 4 - Beta
Classifier: Framework :: Pytest
Classifier: Intended Audience :: Developers
Classifier: Topic :: Software Development :: Testing
Classifier: Programming Language :: Python
Classifier: Programming Language :: Python :: 3
Classifier: Programming Language :: Python :: 3.6
Classifier: Programming Language :: Python :: 3.7
Classifier: Programming Language :: Python :: 3.8
Classifier: Programming Language :: Python :: 3 :: Only
Classifier: Programming Language :: Python :: Implementation :: CPython
Classifier: Programming Language :: Python :: Implementation :: PyPy
Classifier: Operating System :: OS Independent
Classifier: License :: OSI Approved :: BSD License
Requires-Python: >=3.6
Requires-Dist: pytest (>=3.5.0)
